LodashZhongwenWendang45/README.md
LodashZhongwenWendang45/__init__.py
LodashZhongwenWendang45/__main__.py
LodashZhongwenWendang45/file.epub
LodashZhongwenWendang45/index.html
LodashZhongwenWendang45/css/__init__.py
LodashZhongwenWendang45/css/annotations.css
LodashZhongwenWendang45/css/main.css
LodashZhongwenWendang45/css/normalize.css
LodashZhongwenWendang45/css/popup.css
LodashZhongwenWendang45/font/__init__.py
LodashZhongwenWendang45/font/fontello.eot
LodashZhongwenWendang45/font/fontello.svg
LodashZhongwenWendang45/font/fontello.ttf
LodashZhongwenWendang45/font/fontello.woff
LodashZhongwenWendang45/img/__init__.py
LodashZhongwenWendang45/img/annotator-glyph-sprite.png
LodashZhongwenWendang45/img/annotator-icon-sprite.png
LodashZhongwenWendang45/img/apple-touch-icon.png
LodashZhongwenWendang45/img/cancelfullscreen.png
LodashZhongwenWendang45/img/close.png
LodashZhongwenWendang45/img/fullscreen.png
LodashZhongwenWendang45/img/loader.gif
LodashZhongwenWendang45/img/menu-icon.png
LodashZhongwenWendang45/img/save.png
LodashZhongwenWendang45/img/saved.png
LodashZhongwenWendang45/img/settings-s.png
LodashZhongwenWendang45/img/settings.png
LodashZhongwenWendang45/img/star.png
LodashZhongwenWendang45/js/__init__.py
LodashZhongwenWendang45/js/epub.js
LodashZhongwenWendang45/js/epub.min.js
LodashZhongwenWendang45/js/epub.min.map
LodashZhongwenWendang45/js/hooks.min.js
LodashZhongwenWendang45/js/hooks.min.map
LodashZhongwenWendang45/js/reader.js
LodashZhongwenWendang45/js/reader.js.map
LodashZhongwenWendang45/js/reader.min.js
LodashZhongwenWendang45/js/reader.min.map
LodashZhongwenWendang45/js/hooks/__init__.py
LodashZhongwenWendang45/js/hooks/extensions/__init__.py
LodashZhongwenWendang45/js/hooks/extensions/highlight.js
LodashZhongwenWendang45/js/libs/__init__.py
LodashZhongwenWendang45/js/libs/jquery.min.js
LodashZhongwenWendang45/js/libs/localforage.min.js
LodashZhongwenWendang45/js/libs/screenfull.js
LodashZhongwenWendang45/js/libs/screenfull.min.js
lodash_zhongwen_wendang_4_5-2024.2.29.0.dist-info/METADATA
lodash_zhongwen_wendang_4_5-2024.2.29.0.dist-info/WHEEL
lodash_zhongwen_wendang_4_5-2024.2.29.0.dist-info/entry_points.txt
lodash_zhongwen_wendang_4_5-2024.2.29.0.dist-info/top_level.txt
lodash_zhongwen_wendang_4_5-2024.2.29.0.dist-info/RECORD
